thelatinlibrary/__init__.py
thelatinlibrary/api.py
thelatinlibrary/authors.py
thelatinlibrary/exceptions.py
thelatinlibrary/section.py
thelatinlibrary/settings.py
thelatinlibrary/tome.py
thelatinlibrary-0.2.0.dist-info/AUTHORS
thelatinlibrary-0.2.0.dist-info/LICENSE
thelatinlibrary-0.2.0.dist-info/METADATA
thelatinlibrary-0.2.0.dist-info/WHEEL
thelatinlibrary-0.2.0.dist-info/top_level.txt
thelatinlibrary-0.2.0.dist-info/RECORD
