Metadata-Version: 2.1
Name: thelatinlibrary
Version: 0.2.0
Summary: An unofficial thelatinlibrary.com client
Home-page: https://github.com/hearot/thelatinlibrary
Author: hearot
Author-email: gabriel@hearot.it
License: GNU GENERAL PUBLIC LICENSE
Platform: UNKNOWN
Classifier: License :: OSI Approved :: GNU General Public License v3 (GPLv3)
Classifier: Programming Language :: Python
Classifier: Programming Language :: Python :: 3 :: Only
Classifier: Programming Language :: Python :: 3.6
Classifier: Programming Language :: Python :: 3.7
Requires-Python: >=3.6.0
Requires-Dist: BeautifulSoup4
Requires-Dist: dataclasses
Requires-Dist: html5lib
Requires-Dist: requests
